py4agent_mcp/__init__.py
py4agent_mcp/mcp_server.py
py4agent_mcp-0.1.1.dist-info/METADATA
py4agent_mcp-0.1.1.dist-info/WHEEL
py4agent_mcp-0.1.1.dist-info/entry_points.txt
py4agent_mcp-0.1.1.dist-info/RECORD
