Metadata-Version: 2.4
Name: py4agent-mcp
Version: 0.1.1
Summary: MCP (Model Context Protocol) Server for py4agent - Provides code execution capabilities through Jupyter kernels
License-Expression: MIT
Keywords: mcp,jupyter,code-interpreter,ai-agent,code-execution,model-context-protocol
Author: LinXueyuanStdio
Author-email: 23211526+LinXueyuanStdio@users.noreply.github.com
Requires-Python: >=3.9
Classifier: Development Status :: 3 - Alpha
Classifier: Intended Audience :: Developers
Classifier: Programming Language :: Python :: 3
Classifier: Programming Language :: Python :: 3.9
Classifier: Programming Language :: Python :: 3.10
Classifier: Programming Language :: Python :: 3.11
Classifier: Programming Language :: Python :: 3.12
Provides-Extra: dev
Requires-Dist: black ; extra == "dev"
Requires-Dist: mypy ; extra == "dev"
Requires-Dist: pytest ; extra == "dev"
Requires-Dist: pytest-asyncio ; extra == "dev"
Requires-Dist: pytest-cov ; extra == "dev"
Requires-Dist: ruff ; extra == "dev"
